smart_chunker_engine/__init__.py
smart_chunker_engine/boundary_segmenter.py
smart_chunker_engine/exporter.py
smart_chunker_engine/initial_split.py
smart_chunker_engine/iterative_refine.py
smart_chunker_engine/metablock.py
smart_chunker_engine/metadata_builder.py
smart_chunker_engine/metrics.py
smart_chunker_engine/pipeline.py
smart_chunker_engine/pre_normalize.py
smart_chunker_engine/sentence_refine.py
smart_chunker_engine/stats_gate.py
smart_chunker_engine/tfidf_layer.py
smart_chunker_engine/token_pos.py
smart_chunker_engine/triple_cluster.py
smart_chunker_engine/triple_extractor.py
smart_chunker_engine/window_segment.py
tests/__init__.py
tests/conftest.py
tests/test_boundary_segmenter.py
tests/test_evaluate_boundaries.py
tests/test_initial_split.py
tests/test_iterative_refine.py
tests/test_iterative_refine_prod.py
tests/test_metablock.py
tests/test_metadata_builder.py
tests/test_metrics.py
tests/test_metrics_scripts.py
tests/test_pipeline.py
tests/test_pre_normalize.py
tests/test_sentence_refine.py
tests/test_stats_gate.py
tests/test_tfidf_layer.py
tests/test_token_pos.py
tests/test_triple_cluster.py
tests/test_triple_extractor.py
tests/test_window_segment.py
smart_chunker_engine-0.1.0.dist-info/METADATA
smart_chunker_engine-0.1.0.dist-info/WHEEL
smart_chunker_engine-0.1.0.dist-info/top_level.txt
smart_chunker_engine-0.1.0.dist-info/RECORD
