Metadata-Version: 2.4
Name: smart_chunker_engine
Version: 0.1.0
Summary: Modular semantic text chunking framework with rich metadata (ru/en)
Home-page: https://github.com/maverikod/vvz-smart-chunker-engine
Author: Smart Chunker Team
Project-URL: Documentation, https://github.com/maverikod/vvz-smart-chunker-engine
Project-URL: Source, https://github.com/maverikod/vvz-smart-chunker-engine
Classifier: Programming Language :: Python :: 3
Classifier: Operating System :: OS Independent
Classifier: Intended Audience :: Developers
Classifier: License :: OSI Approved :: MIT License
Classifier: Topic :: Text Processing :: Linguistic
Classifier: Framework :: Pytest
Requires-Python: >=3.10
Requires-Dist: chunk_metadata_adapter>=1.3.0
Requires-Dist: sentence-transformers>=2.2.2
Requires-Dist: hdbscan>=0.8.29
Requires-Dist: scikit-learn>=1.0.0
Requires-Dist: spacy>=3.5.0
Dynamic: author
Dynamic: classifier
Dynamic: description
Dynamic: description-content-type
Dynamic: home-page
Dynamic: project-url
Dynamic: requires-dist
Dynamic: requires-python
Dynamic: summary
